LICENSE
MANIFEST.in
README.rst
setup.py
django_lbutils.egg-info/PKG-INFO
django_lbutils.egg-info/SOURCES.txt
django_lbutils.egg-info/dependency_links.txt
django_lbutils.egg-info/not-zip-safe
django_lbutils.egg-info/requires.txt
django_lbutils.egg-info/top_level.txt
lbutils/__init__.py
lbutils/dateutils.py
lbutils/forms.py
lbutils/qs.py
lbutils/utils.py
lbutils/views.py
lbutils/widgets.py
lbutils/xlsxutils.py
lbutils/management/__init__.py
lbutils/management/commands/__init__.py
lbutils/management/commands/callfunc.py
lbutils/templates/bootstrap3/multicolumnsfield.html
lbutils/templatetags/__init__.py
lbutils/templatetags/lbutils.py
lbutils/tests/__init__.py
lbutils/tests/forms.py
lbutils/tests/models.py
lbutils/tests/tests.py